LICENSE
MANIFEST.in
bootstrap.py
buildout.cfg
setup.cfg
setup.py
src/README.txt
src/TODO.txt
src/ikazuchi/__init__.py
src/ikazuchi.plugins.speech.egg-info/PKG-INFO
src/ikazuchi.plugins.speech.egg-info/SOURCES.txt
src/ikazuchi.plugins.speech.egg-info/dependency_links.txt
src/ikazuchi.plugins.speech.egg-info/entry_points.txt
src/ikazuchi.plugins.speech.egg-info/namespace_packages.txt
src/ikazuchi.plugins.speech.egg-info/requires.txt
src/ikazuchi.plugins.speech.egg-info/top_level.txt
src/ikazuchi/plugins/__init__.py
src/ikazuchi/plugins/speech.py
src/ikazuchi/tests/test_pep8.py
src/ikazuchi/tests/test_speech.py
src/ikazuchi/tests/data/speech/hello.mp3
src/ikazuchi/tests/data/speech/hello.wav
src/ikazuchi/tests/data/speech/こんにちは.mp3
src/ikazuchi/tests/data/speech/こんにちは.wav