Metadata-Version: 1.0
Name: ikazuchi.plugins.speech
Version: 0.1.2
Summary: Speech handler with ikazuchi
Home-page: http://t2y.bitbucket.org/ikazuchi/build/html/index.html
Author: Tetsuya Morimoto
Author-email: tetsuya dot morimoto at gmail dot com
License: Apache License 2.0
Keywords: speech
Platform: UNKNOWN
Classifier: Development Status :: 4 - Beta
Classifier: Environment :: Console
Classifier: Intended Audience :: Developers
Classifier: Intended Audience :: System Administrators
Classifier: License :: OSI Approved :: Apache Software License
Classifier: Operating System :: MacOS :: MacOS X
Classifier: Operating System :: Microsoft :: Windows
Classifier: Operating System :: POSIX
Classifier: Programming Language :: Python
Classifier: Topic :: Software Development
Classifier: Topic :: Multimedia :: Sound/Audio :: Speech
